pyRDDLGym_gurobi/__init__.py
pyRDDLGym_gurobi/core/__init__.py
pyRDDLGym_gurobi/core/compiler.py
pyRDDLGym_gurobi/core/planner.py
pyRDDLGym_gurobi/examples/__init__.py
pyRDDLGym_gurobi/examples/default.cfg
pyRDDLGym_gurobi/examples/run_plan.py
pyRDDLGym_gurobi-0.2.dist-info/LICENSE
pyRDDLGym_gurobi-0.2.dist-info/METADATA
pyRDDLGym_gurobi-0.2.dist-info/WHEEL
pyRDDLGym_gurobi-0.2.dist-info/top_level.txt
pyRDDLGym_gurobi-0.2.dist-info/RECORD
