Metadata-Version: 2.1
Name: pyRDDLGym-gurobi
Version: 0.2
Summary: pyRDDLGym-gurobi: Gurobi compilation of RDDL description files, and optimization tools.
Home-page: https://github.com/pyrddlgym-project/pyRDDLGym-gurobi
Author: Michael Gimelfarb, Ayal Taitler, Scott Sanner
Author-email: mike.gimelfarb@mail.utoronto.ca, ataitler@gmail.com, ssanner@mie.utoronto.ca
License: MIT License
Classifier: Development Status :: 4 - Beta
Classifier: Intended Audience :: Science/Research
Classifier: License :: OSI Approved :: MIT License
Classifier: Natural Language :: English
Classifier: Operating System :: OS Independent
Classifier: Programming Language :: Python :: 3
Classifier: Topic :: Scientific/Engineering :: Artificial Intelligence
Requires-Python: >=3.8
License-File: LICENSE
Requires-Dist: pyRDDLGym >=2.0
Requires-Dist: gurobipy >=10.0.0
